[{"n":"activity","c":"misc","t":["activity"]},{"n":"alert","c":"ui","t":["alert"]},{"n":"archive","c":"tech","t":["archive"]},{"n":"arrow-bottom","c":"tech","t":["arrow","bottom"]},{"n":"arrow-left","c":"tech","t":["arrow","left"]},{"n":"arrow-right","c":"tech","t":["arrow","right"]},{"n":"arrow-top","c":"tech","t":["arrow","top"]},{"n":"backwards","c":"tech","t":["backwards"]},{"n":"bag","c":"ecommerce","t":["bag"]},{"n":"ban","c":"misc","t":["ban"]},{"n":"bell","c":"social","t":["bell"]},{"n":"book","c":"education","t":["book"]},{"n":"bookmark","c":"social","t":["bookmark"]},{"n":"calendar","c":"tech","t":["calendar"]},{"n":"camera","c":"media","t":["camera"]},{"n":"caret-bottom","c":"travel","t":["caret","bottom"]},{"n":"caret-left","c":"travel","t":["caret","left"]},{"n":"caret-right","c":"travel","t":["caret","right"]},{"n":"caret-top","c":"travel","t":["caret","top"]},{"n":"cart","c":"travel","t":["cart"]},{"n":"checkmark","c":"tech","t":["checkmark"]},{"n":"chevron-bottom","c":"tech","t":["chevron","bottom"]},{"n":"chevron-left","c":"tech","t":["chevron","left"]},{"n":"chevron-right","c":"tech","t":["chevron","right"]},{"n":"chevron-top","c":"tech","t":["chevron","top"]},{"n":"clipboard","c":"tech","t":["clipboard"]},{"n":"clock","c":"security","t":["clock"]},{"n":"close","c":"misc","t":["close"]},{"n":"code","c":"tech","t":["code"]},{"n":"compose","c":"misc","t":["compose"]},{"n":"creditcard","c":"travel","t":["creditcard"]},{"n":"desktop","c":"tech","t":["desktop"]},{"n":"download","c":"files","t":["download"]},{"n":"edit","c":"misc","t":["edit"]},{"n":"eject","c":"misc","t":["eject"]},{"n":"ellipsis-horizontal","c":"misc","t":["ellipsis","horizontal"]},{"n":"ellipsis-vertical","c":"misc","t":["ellipsis","vertical"]},{"n":"end","c":"misc","t":["end"]},{"n":"export","c":"files","t":["export"]},{"n":"external","c":"misc","t":["external"]},{"n":"eye","c":"health","t":["eye"]},{"n":"feed","c":"misc","t":["feed"]},{"n":"file","c":"files","t":["file"]},{"n":"filter","c":"ui","t":["filter"]},{"n":"fire","c":"misc","t":["fire"]},{"n":"flag","c":"flags","t":["flag"]},{"n":"folder","c":"files","t":["folder"]},{"n":"folder-open","c":"files","t":["folder","open"]},{"n":"forwards","c":"communication","t":["forwards"]},{"n":"fullscreen","c":"tech","t":["fullscreen"]},{"n":"fullscreen-exit","c":"tech","t":["fullscreen","exit"]},{"n":"gift","c":"ecommerce","t":["gift"]},{"n":"github","c":"brands","t":["github"]},{"n":"heart","c":"social","t":["heart"]},{"n":"home","c":"misc","t":["home"]},{"n":"import","c":"files","t":["import"]},{"n":"inbox","c":"communication","t":["inbox"]},{"n":"info","c":"misc","t":["info"]},{"n":"lightning","c":"weather","t":["lightning"]},{"n":"link","c":"misc","t":["link"]},{"n":"location","c":"nature","t":["location"]},{"n":"lock","c":"security","t":["lock"]},{"n":"mail","c":"communication","t":["mail"]},{"n":"menu","c":"ui","t":["menu"]},{"n":"message","c":"social","t":["message"]},{"n":"microphone","c":"communication","t":["microphone"]},{"n":"minus","c":"misc","t":["minus"]},{"n":"mobile","c":"misc","t":["mobile"]},{"n":"moon","c":"weather","t":["moon"]},{"n":"move","c":"arrows","t":["move"]},{"n":"music","c":"media","t":["music"]},{"n":"mute","c":"misc","t":["mute"]},{"n":"options","c":"misc","t":["options"]},{"n":"paperclip","c":"misc","t":["paperclip"]},{"n":"pause","c":"media","t":["pause"]},{"n":"photo","c":"weather","t":["photo"]},{"n":"play","c":"media","t":["play"]},{"n":"plus","c":"misc","t":["plus"]},{"n":"portfolio","c":"business","t":["portfolio"]},{"n":"print","c":"misc","t":["print"]},{"n":"reload","c":"misc","t":["reload"]},{"n":"reply","c":"communication","t":["reply"]},{"n":"search","c":"health","t":["search"]},{"n":"send","c":"communication","t":["send"]},{"n":"settings","c":"ui","t":["settings"]},{"n":"sign-in","c":"business","t":["sign","in"]},{"n":"sign-out","c":"business","t":["sign","out"]},{"n":"star","c":"social","t":["star"]},{"n":"start","c":"social","t":["start"]},{"n":"tag","c":"ecommerce","t":["tag"]},{"n":"telephone","c":"communication","t":["telephone"]},{"n":"trash","c":"misc","t":["trash"]},{"n":"twitter","c":"brands","t":["twitter"]},{"n":"unlock","c":"security","t":["unlock"]},{"n":"upload","c":"files","t":["upload"]},{"n":"user","c":"misc","t":["user"]},{"n":"video","c":"media","t":["video"]},{"n":"volume","c":"misc","t":["volume"]},{"n":"work","c":"misc","t":["work"]},{"n":"zoom-in","c":"brands","t":["zoom","in"]},{"n":"zoom-out","c":"brands","t":["zoom","out"]},{"n":"zoom-reset","c":"brands","t":["zoom","reset"]}]